django_request_id-0.1.0.dist-info/DESCRIPTION.rst
django_request_id-0.1.0.dist-info/METADATA
django_request_id-0.1.0.dist-info/pydist.json
django_request_id-0.1.0.dist-info/RECORD
django_request_id-0.1.0.dist-info/top_level.txt
django_request_id-0.1.0.dist-info/WHEEL
request_id/conf.py
request_id/local.py
request_id/logging.py
request_id/middleware.py
request_id/models.py
request_id/wsgi.py
request_id/__init__.py
request_id/templatetags/request_id.py
request_id/templatetags/__init__.py
