Metadata-Version: 2.0
Name: django-request-id
Version: 0.1.0
Summary: Augment each request with unique id for logging purposes
Home-page: https://github.com/nigma/django-request-id
Author: Filip Wasilewski
Author-email: en@ig.ma
License: MIT
Keywords: django-request-id
Platform: UNKNOWN
Classifier: Development Status :: 3 - Alpha
Classifier: Environment :: Web Environment
Classifier: Framework :: Django
Classifier: Intended Audience :: Developers
Classifier: License :: OSI Approved :: MIT License
Classifier: Operating System :: OS Independent
Classifier: Natural Language :: English
Classifier: Programming Language :: Python :: 2
Classifier: Programming Language :: Python :: 2.7
Classifier: Programming Language :: Python :: 3
Classifier: Programming Language :: Python :: 3.3
Classifier: Topic :: Software Development :: Libraries :: Python Modules
Requires-Dist: django
Requires-Dist: django-appconf (>=0.6)
